DDCO/stopwatch.v
module stopwatch (
    input clk,          // clock input (1 Hz or divided clock)
    input reset,        // reset stopwatch
    input start,        // start counting
    input stop,         // stop counting
    output reg [5:0] sec,  // seconds (0–59)
    output reg [5:0] min   // minutes (0–59)
);

    reg running; // keeps track if stopwatch is running

    always @(posedge clk or posedge reset) begin
        if (reset) begin
            // Reset all values
            sec <= 0;
            min <= 0;
            running <= 0;
        end 
        else begin
            // Control logic
            if (start)
                running <= 1;
            else if (stop)
                running <= 0;

            // Time counting
            if (running) begin
                if (sec == 59) begin
                    sec <= 0;
                    if (min == 59)
                        min <= 0;     // reset after 59:59
                    else
                        min <= min + 1;
                end 
                else begin
                    sec <= sec + 1;
                end
            end
        end
    end
endmodule

DDCO/tb_stopwatch.v
`timescale 1ns/1ps

module stopwatch_tb;
    reg clk, reset, start, stop;
    wire [5:0] sec, min;

    // Instantiate the stopwatch
    stopwatch uut (
        .clk(clk),
        .reset(reset),
        .start(start),
        .stop(stop),
        .sec(sec),
        .min(min)
    );

    // Clock generation: toggle every 5 ns -> 100 MHz
    initial begin
        clk = 0;
        forever #5 clk = ~clk;
    end

    initial begin
        // For GTKWave dump
        $dumpfile("stopwatch.vcd");
        $dumpvars(0, stopwatch_tb);

        // Initialize signals
        reset = 1; start = 0; stop = 0;
        #20 reset = 0;    // Release reset after 20 ns

        #20 start = 1;    // Start counting
        #10 start = 0;    // Pulse style start button

        // Let it run for a while
        #600 stop = 1;    // Stop after ~600 ns
        #10 stop = 0;

        #100 start = 1;   // Start again
        #10 start = 0;

        #300 reset = 1;   // Reset stopwatch
        #20 reset = 0;

        #200 $finish;     // End simulation
    end

    // Display output on console
    initial begin
        $monitor("T=%0t | running=%b | min=%0d | sec=%0d", 
                 $time, uut.running, min, sec);
    end
endmodule

DDCO/stopwatch.vcd
$date
	Thu Nov 13 11:39:13 2025
$end
$version
	Icarus Verilog
$end
$timescale
	1ps
$end
$scope module stopwatch_tb $end
$var wire 6 ! sec [5:0] $end
$var wire 6 " min [5:0] $end
$var reg 1 # clk $end
$var reg 1 $ reset $end
$var reg 1 % start $end
$var reg 1 & stop $end
$scope module uut $end
$var wire 1 # clk $end
$var wire 1 $ reset $end
$var wire 1 % start $end
$var wire 1 & stop $end
$var reg 6 ' min [5:0] $end
$var reg 1 ( running $end
$var reg 6 ) sec [5:0] $end
$upscope $end
$upscope $end
$enddefinitions $end
$comment Show the parameter values. $end
$dumpall
$end
#0
$dumpvars
b0 )
0(
b0 '
0&
0%
1$
0#
b0 "
b0 !
$end
#5000
1#
#10000
0#
#15000
1#
#20000
0#
0$
#25000
1#
#30000
0#
#35000
1#
#40000
0#
1%
#45000
1(
1#
#50000
0#
0%
#55000
b1 !
b1 )
1#
#60000
0#
#65000
b10 !
b10 )
1#
#70000
0#
#75000
b11 !
b11 )
1#
#80000
0#
#85000
b100 !
b100 )
1#
#90000
0#
#95000
b101 !
b101 )
1#
#100000
0#
#105000
b110 !
b110 )
1#
#110000
0#
#115000
b111 !
b111 )
1#
#120000
0#
#125000
b1000 !
b1000 )
1#
#130000
0#
#135000
b1001 !
b1001 )
1#
#140000
0#
#145000
b1010 !
b1010 )
1#
#150000
0#
#155000
b1011 !
b1011 )
1#
#160000
0#
#165000
b1100 !
b1100 )
1#
#170000
0#
#175000
b1101 !
b1101 )
1#
#180000
0#
#185000
b1110 !
b1110 )
1#
#190000
0#
#195000
b1111 !
b1111 )
1#
#200000
0#
#205000
b10000 !
b10000 )
1#
#210000
0#
#215000
b10001 !
b10001 )
1#
#220000
0#
#225000
b10010 !
b10010 )
1#
#230000
0#
#235000
b10011 !
b10011 )
1#
#240000
0#
#245000
b10100 !
b10100 )
1#
#250000
0#
#255000
b10101 !
b10101 )
1#
#260000
0#
#265000
b10110 !
b10110 )
1#
#270000
0#
#275000
b10111 !
b10111 )
1#
#280000
0#
#285000
b11000 !
b11000 )
1#
#290000
0#
#295000
b11001 !
b11001 )
1#
#300000
0#
#305000
b11010 !
b11010 )
1#
#310000
0#
#315000
b11011 !
b11011 )
1#
#320000
0#
#325000
b11100 !
b11100 )
1#
#330000
0#
#335000
b11101 !
b11101 )
1#
#340000
0#
#345000
b11110 !
b11110 )
1#
#350000
0#
#355000
b11111 !
b11111 )
1#
#360000
0#
#365000
b100000 !
b100000 )
1#
#370000
0#
#375000
b100001 !
b100001 )
1#
#380000
0#
#385000
b100010 !
b100010 )
1#
#390000
0#
#395000
b100011 !
b100011 )
1#
#400000
0#
#405000
b100100 !
b100100 )
1#
#410000
0#
#415000
b100101 !
b100101 )
1#
#420000
0#
#425000
b100110 !
b100110 )
1#
#430000
0#
#435000
b100111 !
b100111 )
1#
#440000
0#
#445000
b101000 !
b101000 )
1#
#450000
0#
#455000
b101001 !
b101001 )
1#
#460000
0#
#465000
b101010 !
b101010 )
1#
#470000
0#
#475000
b101011 !
b101011 )
1#
#480000
0#
#485000
b101100 !
b101100 )
1#
#490000
0#
#495000
b101101 !
b101101 )
1#
#500000
0#
#505000
b101110 !
b101110 )
1#
#510000
0#
#515000
b101111 !
b101111 )
1#
#520000
0#
#525000
b110000 !
b110000 )
1#
#530000
0#
#535000
b110001 !
b110001 )
1#
#540000
0#
#545000
b110010 !
b110010 )
1#
#550000
0#
#555000
b110011 !
b110011 )
1#
#560000
0#
#565000
b110100 !
b110100 )
1#
#570000
0#
#575000
b110101 !
b110101 )
1#
#580000
0#
#585000
b110110 !
b110110 )
1#
#590000
0#
#595000
b110111 !
b110111 )
1#
#600000
0#
#605000
b111000 !
b111000 )
1#
#610000
0#
#615000
b111001 !
b111001 )
1#
#620000
0#
#625000
b111010 !
b111010 )
1#
#630000
0#
#635000
b111011 !
b111011 )
1#
#640000
0#
#645000
b1 "
b1 '
b0 !
b0 )
1#
#650000
0#
1&
#655000
b1 !
b1 )
0(
1#
#660000
0#
0&
#665000
1#
#670000
0#
#675000
1#
#680000
0#
#685000
1#
#690000
0#
#695000
1#
#700000
0#
#705000
1#
#710000
0#
#715000
1#
#720000
0#
#725000
1#
#730000
0#
#735000
1#
#740000
0#
#745000
1#
#750000
0#
#755000
1#
#760000
0#
1%
#765000
1(
1#
#770000
0#
0%
#775000
b10 !
b10 )
1#
#780000
0#
#785000
b11 !
b11 )
1#
#790000
0#
#795000
b100 !
b100 )
1#
#800000
0#
#805000
b101 !
b101 )
1#
#810000
0#
#815000
b110 !
b110 )
1#
#820000
0#
#825000
b111 !
b111 )
1#
#830000
0#
#835000
b1000 !
b1000 )
1#
#840000
0#
#845000
b1001 !
b1001 )
1#
#850000
0#
#855000
b1010 !
b1010 )
1#
#860000
0#
#865000
b1011 !
b1011 )
1#
#870000
0#
#875000
b1100 !
b1100 )
1#
#880000
0#
#885000
b1101 !
b1101 )
1#
#890000
0#
#895000
b1110 !
b1110 )
1#
#900000
0#
#905000
b1111 !
b1111 )
1#
#910000
0#
#915000
b10000 !
b10000 )
1#
#920000
0#
#925000
b10001 !
b10001 )
1#
#930000
0#
#935000
b10010 !
b10010 )
1#
#940000
0#
#945000
b10011 !
b10011 )
1#
#950000
0#
#955000
b10100 !
b10100 )
1#
#960000
0#
#965000
b10101 !
b10101 )
1#
#970000
0#
#975000
b10110 !
b10110 )
1#
#980000
0#
#985000
b10111 !
b10111 )
1#
#990000
0#
#995000
b11000 !
b11000 )
1#
#1000000
0#
#1005000
b11001 !
b11001 )
1#
#1010000
0#
#1015000
b11010 !
b11010 )
1#
#1020000
0#
#1025000
b11011 !
b11011 )
1#
#1030000
0#
#1035000
b11100 !
b11100 )
1#
#1040000
0#
#1045000
b11101 !
b11101 )
1#
#1050000
0#
#1055000
b11110 !
b11110 )
1#
#1060000
0#
#1065000
b11111 !
b11111 )
1#
#1070000
0(
b0 "
b0 '
b0 !
b0 )
0#
1$
#1075000
1#
#1080000
0#
#1085000
1#
#1090000
0#
0$
